{
	"version": 1,
	"allow_edit": true,
	"plugins": [],
	"panes": [
		{
			"title": "Date time",
			"width": 1,
			"row": {
				"3": 13
			},
			"col": {
				"3": 1
			},
			"col_width": 1,
			"widgets": [
				{
					"type": "text_widget",
					"settings": {
						"title": "Date",
						"size": "regular",
						"value": "datasources[\"CurrentTime\"][\"date_string_value\"]",
						"animate": false
					}
				},
				{
					"type": "text_widget",
					"settings": {
						"title": "Hour",
						"size": "regular",
						"value": "datasources[\"CurrentTime\"][\"time_string_value\"]",
						"sparkline": false,
						"animate": false,
						"units": ""
					}
				}
			]
		},
		{
			"title": "Weather",
			"width": 1,
			"row": {
				"3": 1
			},
			"col": {
				"3": 2
			},
			"col_width": 1,
			"widgets": [
				{
					"type": "text_widget",
					"settings": {
						"size": "regular",
						"value": "datasources[\"WeatherParis\"][\"place_name\"]",
						"animate": true
					}
				},
				{
					"type": "indicator",
					"settings": {
						"value": "datasources[\"WeatherParis\"][\"conditions\"]",
						"on_text": "datasources[\"WeatherParis\"][\"conditions\"]"
					}
				},
				{
					"type": "text_widget",
					"settings": {
						"title": "Current temperature",
						"size": "regular",
						"value": "datasources[\"WeatherParis\"][\"current_temp\"]",
						"sparkline": false,
						"animate": true,
						"units": "°C"
					}
				},
				{
					"type": "text_widget",
					"settings": {
						"title": "Humidity",
						"size": "regular",
						"value": "datasources[\"WeatherParis\"][\"humidity\"]",
						"sparkline": false,
						"animate": true,
						"units": "%"
					}
				},
				{
					"type": "text_widget",
					"settings": {
						"title": "Pressure",
						"size": "regular",
						"value": "datasources[\"WeatherParis\"][\"pressure\"]",
						"sparkline": false,
						"animate": true,
						"units": "hPa"
					}
				},
				{
					"type": "text_widget",
					"settings": {
						"title": "Wind",
						"size": "regular",
						"value": "datasources[\"WeatherParis\"][\"wind_speed\"]",
						"sparkline": false,
						"animate": true,
						"units": "m/s"
					}
				}
			]
		},
		{
			"title": "Sun",
			"width": 1,
			"row": {
				"3": 19
			},
			"col": {
				"3": 1
			},
			"col_width": 1,
			"widgets": [
				{
					"type": "text_widget",
					"settings": {
						"size": "regular",
						"value": "datasources[\"WeatherParis\"][\"place_name\"]",
						"animate": true
					}
				},
				{
					"type": "text_widget",
					"settings": {
						"title": "Sunrise",
						"size": "regular",
						"value": "datasources[\"WeatherParis\"][\"sunrise\"]",
						"animate": true
					}
				},
				{
					"type": "text_widget",
					"settings": {
						"title": "Sunset",
						"size": "regular",
						"value": "datasources[\"WeatherParis\"][\"sunset\"]",
						"animate": true
					}
				}
			]
		},
		{
			"title": "Github",
			"width": 1,
			"row": {
				"3": 1
			},
			"col": {
				"3": 3
			},
			"col_width": 1,
			"widgets": [
				{
					"type": "text_widget",
					"settings": {
						"size": "regular",
						"value": "datasources[\"Github simplecountdown\"][1][\"total\"]",
						"animate": true
					}
				}
			]
		},
		{
			"title": "Presentation",
			"width": 1,
			"row": {
				"3": 1
			},
			"col": {
				"3": 1
			},
			"col_width": 1,
			"widgets": [
				{
					"type": "picture",
					"settings": {
						"src": "https://secure.gravatar.com/avatar/bf1a732de7305fe166047d8360329377?size=300",
						"refresh": 0
					}
				},
				{
					"type": "text_widget",
					"settings": {
						"size": "regular",
						"value": "datasources[\"Gravatar\"][\"entry\"][0][\"name\"][\"formatted\"]",
						"animate": true
					}
				}
			]
		}
	],
	"datasources": [
		{
			"name": "CurrentTime",
			"type": "clock",
			"settings": {
				"refresh": 1
			}
		},
		{
			"name": "WeatherParis",
			"type": "openweathermap",
			"settings": {
				"api_key": "9244637da163c04698371dead74eeb9a",
				"location": "Paris, France",
				"units": "metric",
				"refresh": 30,
				"name": "WeatherParis"
			}
		},
		{
			"name": "Github simplecountdown",
			"type": "JSON",
			"settings": {
				"url": "https://api.github.com/repos/bhagenbourger/simplecountdown/stats/contributors",
				"use_thingproxy": true,
				"refresh": 5,
				"method": "GET"
			}
		},
		{
			"name": "Gravatar",
			"type": "JSON",
			"settings": {
				"url": "https://fr.gravatar.com/bhagenbourger.json",
				"use_thingproxy": true,
				"refresh": 86400,
				"method": "GET",
				"headers": [
					{
						"name": "Access-Control-Allow-Origin",
						"value": "*"
					}
				]
			}
		}
	],
	"columns": 3
}
